hopsy/__init__.py
hopsy/callback.py
hopsy/core.cpython-39-darwin.so
hopsy/definitions.py
hopsy/examples.py
hopsy/lp.py
hopsy/misc.py
hopsy/setup.py
hopsy/tuning.py
hopsy-1.6.1.dist-info/licenses/LICENSE
hopsy-1.6.1.dist-info/METADATA
hopsy-1.6.1.dist-info/WHEEL
hopsy-1.6.1.dist-info/top_level.txt
hopsy-1.6.1.dist-info/RECORD
