Metadata-Version: 2.1
Name: hopsy
Version: 1.6.1
Summary: A python interface for hops, the highly optimized polytope sampling toolbox.
Author: Richard D. Paul
Author-email: r.paul@fz-juelich.de
Project-URL: Documentation, https://modsim.github.io/hopsy/
Project-URL: Gitlab (Sources&CI), https://jugit.fz-juelich.de/IBG-1/ModSim/hopsy
Project-URL: GitHub (Mirror), https://github.com/modsim/hopsy/
Classifier: Programming Language :: Python :: 3
Classifier: Operating System :: POSIX :: Linux
License-File: LICENSE
